CRYSTALpytools/__init__.py
CRYSTALpytools/adsorb.py
CRYSTALpytools/calculate.py
CRYSTALpytools/convert.py
CRYSTALpytools/crystal_io.py
CRYSTALpytools/elastics.py
CRYSTALpytools/electronics.py
CRYSTALpytools/execute.py
CRYSTALpytools/geometry.py
CRYSTALpytools/phonons.py
CRYSTALpytools/plot.py
CRYSTALpytools/relativistics.py
CRYSTALpytools/spectra.py
CRYSTALpytools/thermodynamics.py
CRYSTALpytools/topond.py
CRYSTALpytools/transport.py
CRYSTALpytools/units.py
CRYSTALpytools/utils.py
CRYSTALpytools/base/__init__.py
CRYSTALpytools/base/basisset.py
CRYSTALpytools/base/crysd12.py
CRYSTALpytools/base/dump.py
CRYSTALpytools/base/extfmt.py
CRYSTALpytools/base/inputbase.py
CRYSTALpytools/base/output.py
CRYSTALpytools/base/plotbase.py
CRYSTALpytools/base/propd3.py
CRYSTALpytools/io/__init__.py
CRYSTALpytools/io/phonopy.py
CRYSTALpytools/io/xcrysden.py
crystalpytools-2025.5.3.dist-info/licenses/LICENSE.txt
crystalpytools-2025.5.3.dist-info/METADATA
crystalpytools-2025.5.3.dist-info/WHEEL
crystalpytools-2025.5.3.dist-info/top_level.txt
crystalpytools-2025.5.3.dist-info/RECORD
